{"id": "2u_pEd4_2cI", "title": "CHUY LIZARRAGA - LA BUCHONA con letra", "formats": [{"asr": 48000, "filesize": 1092018, "format_id": "249", "format_note": "tiny", "fps": null, "height": null, "quality": 0, "tbr": 47.571, "url": "https://rr7---sn-0opoxu-ihvr.googlevideo.com/videoplayback?expire=1670704945&ei=0ZqUY--1JtKtkgb9o6G4Cw&ip=189.173.225.87&id=o-AE0a5LPaEq35nQxd-T_v8UhtPpD_44qWwlufXywortPl&itag=249&source=youtube&requiressl=yes&mh=Pw&mm=31%2C29&mn=sn-0opoxu-ihvr%2Csn-q4fl6nlz&ms=au%2Crdu&mv=m&mvi=7&pl=24&initcwndbps=831250&vprv=1&mime=audio%2Fwebm&ns=O2TZKNuLSWPWVO3eMbZEI54J&gir=yes&clen=1092018&dur=183.641&lmt=1497149019273444&mt=1670683038&fvip=4&keepalive=yes&fexp=24001373%2C24007246&c=WEB&n=Q1clxY75jYTz5-Jjs&sparams=expire%2Cei%2Cip%2Cid%2Citag%2Csource%2Crequiressl%2Cvprv%2Cmime%2Cns%2Cgir%2Cclen%2Cdur%2Clmt&lsparams=mh%2Cmm%2Cmn%2Cms%2Cmv%2Cmvi%2Cpl%2Cinitcwndbps&lsig=AG3C_xAwRgIhAI7Glh37I9zJmzzy7RE3nkIIWuwMmLLjH9cGoA8fo9F1AiEA9awUjLHecq7HFYxi4H4EnICDxmLUel3wAcp7EViGdqY%3D&sig=AOq0QJ8wRQIhAOiHXeZGFlluOau9CWSDgGPuMxM0y4jwCFAEP9o4ioZbAiA-IT6G2Kl93k03h8LJGUbBnj2Veyg6XMRxI67C-js6gg==", "width": null, "ext": "webm", "vcodec": "none", "acodec": "opus", "abr": 47.571, "downloader_options": {"http_chunk_size": 10485760}, "container": "webm_dash", "format": "249 - audio only (tiny)", "protocol": "https", "http_headers": {"User-Agent": "Mozilla/5.0 (Windows NT 10.0; Win64; x64) AppleWebKit/537.36 (KHTML, like Gecko) Chrome/75.0.3761.3 Safari/537.36", "Accept-Charset": "ISO-8859-1,utf-8;q=0.7,*;q=0.7", "Accept": "text/html,application/xhtml+xml,application/xml;q=0.9,*/*;q=0.8", "Accept-Encoding": "gzip, deflate", "Accept-Language": "en-us,en;q=0.5"}}, {"asr": 48000, "filesize": 1420611, "format_id": "250", "format_note": "tiny", "fps": null, "height": null, "quality": 0, "tbr": 61.886, "url": "https://rr7---sn-0opoxu-ihvr.googlevideo.com/videoplayback?expire=1670704945&ei=0ZqUY--1JtKtkgb9o6G4Cw&ip=189.173.225.87&id=o-AE0a5LPaEq35nQxd-T_v8UhtPpD_44qWwlufXywortPl&itag=250&source=youtube&requiressl=yes&mh=Pw&mm=31%2C29&mn=sn-0opoxu-ihvr%2Csn-q4fl6nlz&ms=au%2Crdu&mv=m&mvi=7&pl=24&initcwndbps=831250&vprv=1&mime=audio%2Fwebm&ns=O2TZKNuLSWPWVO3eMbZEI54J&gir=yes&clen=1420611&dur=183.641&lmt=1497149018584586&mt=1670683038&fvip=4&keepalive=yes&fexp=24001373%2C24007246&c=WEB&n=Q1clxY75jYTz5-Jjs&sparams=expire%2Cei%2Cip%2Cid%2Citag%2Csource%2Crequiressl%2Cvprv%2Cmime%2Cns%2Cgir%2Cclen%2Cdur%2Clmt&lsparams=mh%2Cmm%2Cmn%2Cms%2Cmv%2Cmvi%2Cpl%2Cinitcwndbps&lsig=AG3C_xAwRgIhAPU7VhU3gqsnoikVMvPnz0DisWcmzGtQ07nheQpY8Jh4AiEAxH3BMwMNS_toElqmR_nrxMwiJbK9N_zvz8vw3LCHruQ%3D&sig=AOq0QJ8wRAIgePuJZRkr1TT-_srzjLqwkdlS-Q1OZC2CdPuUk4chxRECIDePh8aFHanI6zhcU6sMqr31EW2mpYe9xEdnMx8rO-Ij", "width": null, "ext": "webm", "vcodec": "none", "acodec": "opus", "abr": 61.886, "downloader_options": {"http_chunk_size": 10485760}, "container": "webm_dash", "format": "250 - audio only (tiny)", "protocol": "https", "http_headers": {"User-Agent": "Mozilla/5.0 (Windows NT 10.0; Win64; x64) AppleWebKit/537.36 (KHTML, like Gecko) Chrome/75.0.3761.3 Safari/537.36", "Accept-Charset": "ISO-8859-1,utf-8;q=0.7,*;q=0.7", "Accept": "text/html,application/xhtml+xml,application/xml;q=0.9,*/*;q=0.8", "Accept-Encoding": "gzip, deflate", "Accept-Language": "en-us,en;q=0.5"}}, {"asr": 48000, "filesize": 2835696, "format_id": "251", "format_note": "tiny", "fps": null, "height": null, "quality": 0, "tbr": 123.532, "url": "https://rr7---sn-0opoxu-ihvr.googlevideo.com/videoplayback?expire=1670704945&ei=0ZqUY--1JtKtkgb9o6G4Cw&ip=189.173.225.87&id=o-AE0a5LPaEq35nQxd-T_v8UhtPpD_44qWwlufXywortPl&itag=251&source=youtube&requiressl=yes&mh=Pw&mm=31%2C29&mn=sn-0opoxu-ihvr%2Csn-q4fl6nlz&ms=au%2Crdu&mv=m&mvi=7&pl=24&initcwndbps=831250&vprv=1&mime=audio%2Fwebm&ns=O2TZKNuLSWPWVO3eMbZEI54J&gir=yes&clen=2835696&dur=183.641&lmt=1497149019963765&mt=1670683038&fvip=4&keepalive=yes&fexp=24001373%2C24007246&c=WEB&n=Q1clxY75jYTz5-Jjs&sparams=expire%2Cei%2Cip%2Cid%2Citag%2Csource%2Crequiressl%2Cvprv%2Cmime%2Cns%2Cgir%2Cclen%2Cdur%2Clmt&lsparams=mh%2Cmm%2Cmn%2Cms%2Cmv%2Cmvi%2Cpl%2Cinitcwndbps&lsig=AG3C_xAwRgIhAMMaZPQ_USu5ADIVpjS2PjJOs22Aza-5N23RbcjW-Z0iAiEAr33mVVkCVw6gjZZ9qXksw6l7mDKIb7SlpAzhHL43cGw%3D&sig=AOq0QJ8wRQIhAIZyNImrNRT3ovrzALA6FiEu5zorP79eOXgtdovoNa4SAiB0W49mVgPsYqb73fuo6ouw1m2uxnx5E7F4YlaHbxBGfQ==", "width": null, "ext": "webm", "vcodec": "none", "acodec": "opus", "abr": 123.532, "downloader_options": {"http_chunk_size": 10485760}, "container": "webm_dash", "format": "251 - audio only (tiny)", "protocol": "https", "http_headers": {"User-Agent": "Mozilla/5.0 (Windows NT 10.0; Win64; x64) AppleWebKit/537.36 (KHTML, like Gecko) Chrome/75.0.3761.3 Safari/537.36", "Accept-Charset": "ISO-8859-1,utf-8;q=0.7,*;q=0.7", "Accept": "text/html,application/xhtml+xml,application/xml;q=0.9,*/*;q=0.8", "Accept-Encoding": "gzip, deflate", "Accept-Language": "en-us,en;q=0.5"}}, {"asr": 44100, "filesize": 2918107, "format_id": "140", "format_note": "tiny", "fps": null, "height": null, "quality": 0, "tbr": 127.086, "url": "https://rr7---sn-0opoxu-ihvr.googlevideo.com/videoplayback?expire=1670704945&ei=0ZqUY--1JtKtkgb9o6G4Cw&ip=189.173.225.87&id=o-AE0a5LPaEq35nQxd-T_v8UhtPpD_44qWwlufXywortPl&itag=140&source=youtube&requiressl=yes&mh=Pw&mm=31%2C29&mn=sn-0opoxu-ihvr%2Csn-q4fl6nlz&ms=au%2Crdu&mv=m&mvi=7&pl=24&initcwndbps=831250&vprv=1&mime=audio%2Fmp4&ns=O2TZKNuLSWPWVO3eMbZEI54J&gir=yes&clen=2918107&dur=183.693&lmt=1394698809491352&mt=1670683038&fvip=4&keepalive=yes&fexp=24001373%2C24007246&c=WEB&n=Q1clxY75jYTz5-Jjs&sparams=expire%2Cei%2Cip%2Cid%2Citag%2Csource%2Crequiressl%2Cvprv%2Cmime%2Cns%2Cgir%2Cclen%2Cdur%2Clmt&lsparams=mh%2Cmm%2Cmn%2Cms%2Cmv%2Cmvi%2Cpl%2Cinitcwndbps&lsig=AG3C_xAwRQIhAI47k3xm-jrX8WLSvyUCa8tuL44VHURr0ZFqVxM4pkydAiAcP1ijy3rUeGUfpxfxX1BjE_mU_969HKz26SswxAD7oA%3D%3D&sig=AOq0QJ8wRQIhAIrddI58_NfxSHSxcLkXMrfplx00Ecq4YdJBtWOzjcDaAiBgwSNXwtSIULITucjRJAIcFsw5xmDnlVmjQ8aSBBon0g==", "width": null, "ext": "m4a", "vcodec": "none", "acodec": "mp4a.40.2", "abr": 127.086, "downloader_options": {"http_chunk_size": 10485760}, "container": "m4a_dash", "format": "140 - audio only (tiny)", "protocol": "https", "http_headers": {"User-Agent": "Mozilla/5.0 (Windows NT 10.0; Win64; x64) AppleWebKit/537.36 (KHTML, like Gecko) Chrome/75.0.3761.3 Safari/537.36", "Accept-Charset": "ISO-8859-1,utf-8;q=0.7,*;q=0.7", "Accept": "text/html,application/xhtml+xml,application/xml;q=0.9,*/*;q=0.8", "Accept-Encoding": "gzip, deflate", "Accept-Language": "en-us,en;q=0.5"}}, {"asr": null, "filesize": 532925, "format_id": "278", "format_note": "144p", "fps": 30, "height": 144, "quality": 0, "tbr": 23.229, "url": "https://rr7---sn-0opoxu-ihvr.googlevideo.com/videoplayback?expire=1670704945&ei=0ZqUY--1JtKtkgb9o6G4Cw&ip=189.173.225.87&id=o-AE0a5LPaEq35nQxd-T_v8UhtPpD_44qWwlufXywortPl&itag=278&aitags=133%2C134%2C135%2C160%2C242%2C243%2C244%2C278%2C394%2C395%2C396%2C397&source=youtube&requiressl=yes&mh=Pw&mm=31%2C29&mn=sn-0opoxu-ihvr%2Csn-q4fl6nlz&ms=au%2Crdu&mv=m&mvi=7&pl=24&initcwndbps=831250&vprv=1&mime=video%2Fwebm&ns=O2TZKNuLSWPWVO3eMbZEI54J&gir=yes&clen=532925&dur=183.533&lmt=1497149188458275&mt=1670683038&fvip=4&keepalive=yes&fexp=24001373%2C24007246&c=WEB&n=Q1clxY75jYTz5-Jjs&sparams=expire%2Cei%2Cip%2Cid%2Caitags%2Csource%2Crequiressl%2Cvprv%2Cmime%2Cns%2Cgir%2Cclen%2Cdur%2Clmt&lsparams=mh%2Cmm%2Cmn%2Cms%2Cmv%2Cmvi%2Cpl%2Cinitcwndbps&lsig=AG3C_xAwRgIhALQ2Vb0pU9wu2Ygxji1oGF15DlRmB-e--enV69HUq0TlAiEAoNDYmUXyOHJlkkh4kX7mLZ8ODUorNwvHBvxnZvqEi8Y%3D&sig=AOq0QJ8wRAIgTy85Tq6URxnNQq-AXQgfPQs_oqFkeHQrS5yXj9yTOk8CIDeGZrsTCsZ1T-6eGA4Drb6TYd-qpalTfdLUZadjPFcg", "width": 192, "ext": "webm", "vcodec": "vp9", "acodec": "none", "vbr": 23.229, "downloader_options": {"http_chunk_size": 10485760}, "container": "webm_dash", "format": "278 - 192x144 (144p)", "protocol": "https", "http_headers": {"User-Agent": "Mozilla/5.0 (Windows NT 10.0; Win64; x64) AppleWebKit/537.36 (KHTML, like Gecko) Chrome/75.0.3761.3 Safari/537.36", "Accept-Charset": "ISO-8859-1,utf-8;q=0.7,*;q=0.7", "Accept": "text/html,application/xhtml+xml,application/xml;q=0.9,*/*;q=0.8", "Accept-Encoding": "gzip, deflate", "Accept-Language": "en-us,en;q=0.5"}}, {"asr": null, "filesize": 666854, "format_id": "394", "format_note": "144p", "fps": 30, "height": 144, "quality": 0, "tbr": 29.062, "url": "https://rr7---sn-0opoxu-ihvr.googlevideo.com/videoplayback?expire=1670704945&ei=0ZqUY--1JtKtkgb9o6G4Cw&ip=189.173.225.87&id=o-AE0a5LPaEq35nQxd-T_v8UhtPpD_44qWwlufXywortPl&itag=394&aitags=133%2C134%2C135%2C160%2C242%2C243%2C244%2C278%2C394%2C395%2C396%2C397&source=youtube&requiressl=yes&mh=Pw&mm=31%2C29&mn=sn-0opoxu-ihvr%2Csn-q4fl6nlz&ms=au%2Crdu&mv=m&mvi=7&pl=24&initcwndbps=831250&vprv=1&mime=video%2Fmp4&ns=O2TZKNuLSWPWVO3eMbZEI54J&gir=yes&clen=666854&dur=183.566&lmt=1626223347490005&mt=1670683038&fvip=4&keepalive=yes&fexp=24001373%2C24007246&c=WEB&txp=5436432&n=Q1clxY75jYTz5-Jjs&sparams=expire%2Cei%2Cip%2Cid%2Caitags%2Csource%2Crequiressl%2Cvprv%2Cmime%2Cns%2Cgir%2Cclen%2Cdur%2Clmt&lsparams=mh%2Cmm%2Cmn%2Cms%2Cmv%2Cmvi%2Cpl%2Cinitcwndbps&lsig=AG3C_xAwRAIgI-xLeBKBHhG05zdGeX6hQwi30mV9tl1LmtLvvig8b8MCIAdv3cU6n7YCJtfKGt279Xt5Y48nPOnHtRdH6G-0bYSv&sig=AOq0QJ8wRQIhAO1S0l_Ny8vIfzOAAgCj6lml8JT1jd6JpRW59g7CL1h_AiB70qwd7jia2nZZEWszJ7tJhqhWjAPEDUDlPebeqBMaoQ==", "width": 192, "ext": "mp4", "vcodec": "av01.0.00M.08", "acodec": "none", "vbr": 29.062, "downloader_options": {"http_chunk_size": 10485760}, "container": "mp4_dash", "format": "394 - 192x144 (144p)", "protocol": "https", "http_headers": {"User-Agent": "Mozilla/5.0 (Windows NT 10.0; Win64; x64) AppleWebKit/537.36 (KHTML, like Gecko) Chrome/75.0.3761.3 Safari/537.36", "Accept-Charset": "ISO-8859-1,utf-8;q=0.7,*;q=0.7", "Accept": "text/html,application/xhtml+xml,application/xml;q=0.9,*/*;q=0.8", "Accept-Encoding": "gzip, deflate", "Accept-Language": "en-us,en;q=0.5"}}, {"asr": null, "filesize": 1189990, "format_id": "160", "format_note": "144p", "fps": 15, "height": 144, "quality": 0, "tbr": 51.87, "url": "https://rr7---sn-0opoxu-ihvr.googlevideo.com/videoplayback?expire=1670704945&ei=0ZqUY--1JtKtkgb9o6G4Cw&ip=189.173.225.87&id=o-AE0a5LPaEq35nQxd-T_v8UhtPpD_44qWwlufXywortPl&itag=160&aitags=133%2C134%2C135%2C160%2C242%2C243%2C244%2C278%2C394%2C395%2C396%2C397&source=youtube&requiressl=yes&mh=Pw&mm=31%2C29&mn=sn-0opoxu-ihvr%2Csn-q4fl6nlz&ms=au%2Crdu&mv=m&mvi=7&pl=24&initcwndbps=831250&vprv=1&mime=video%2Fmp4&ns=O2TZKNuLSWPWVO3eMbZEI54J&gir=yes&clen=1189990&dur=183.534&lmt=1394698809957259&mt=1670683038&fvip=4&keepalive=yes&fexp=24001373%2C24007246&c=WEB&n=Q1clxY75jYTz5-Jjs&sparams=expire%2Cei%2Cip%2Cid%2Caitags%2Csource%2Crequiressl%2Cvprv%2Cmime%2Cns%2Cgir%2Cclen%2Cdur%2Clmt&lsparams=mh%2Cmm%2Cmn%2Cms%2Cmv%2Cmvi%2Cpl%2Cinitcwndbps&lsig=AG3C_xAwRgIhALflCkzY1EmqguOvd9TqcDHD72pMBRUnqxB5VNKlzlhAAiEAkRLy1fzIFNQZI05EqcJbPVDpRHXtVhyeiKr52aFoZxE%3D&sig=AOq0QJ8wRAIgaNyKjJrcYnqMzb8woe9u18Irm86oFtWvxlqBcIjsMxsCIAOt0vru4bdo9pvlo9ZxHOH5kZINHqDo1F9uEL6Vl2yS", "width": 192, "ext": "mp4", "vcodec": "avc1.4d400c", "acodec": "none", "vbr": 51.87, "downloader_options": {"http_chunk_size": 10485760}, "container": "mp4_dash", "format": "160 - 192x144 (144p)", "protocol": "https", "http_headers": {"User-Agent": "Mozilla/5.0 (Windows NT 10.0; Win64; x64) AppleWebKit/537.36 (KHTML, like Gecko) Chrome/75.0.3761.3 Safari/537.36", "Accept-Charset": "ISO-8859-1,utf-8;q=0.7,*;q=0.7", "Accept": "text/html,application/xhtml+xml,application/xml;q=0.9,*/*;q=0.8", "Accept-Encoding": "gzip, deflate", "Accept-Language": "en-us,en;q=0.5"}}, {"asr": null, "filesize": 1030206, "format_id": "242", "format_note": "240p", "fps": 30, "height": 240, "quality": 1, "tbr": 44.905, "url": "https://rr7---sn-0opoxu-ihvr.googlevideo.com/videoplayback?expire=1670704945&ei=0ZqUY--1JtKtkgb9o6G4Cw&ip=189.173.225.87&id=o-AE0a5LPaEq35nQxd-T_v8UhtPpD_44qWwlufXywortPl&itag=242&aitags=133%2C134%2C135%2C160%2C242%2C243%2C244%2C278%2C394%2C395%2C396%2C397&source=youtube&requiressl=yes&mh=Pw&mm=31%2C29&mn=sn-0opoxu-ihvr%2Csn-q4fl6nlz&ms=au%2Crdu&mv=m&mvi=7&pl=24&initcwndbps=831250&vprv=1&mime=video%2Fwebm&ns=O2TZKNuLSWPWVO3eMbZEI54J&gir=yes&clen=1030206&dur=183.533&lmt=1497149186527325&mt=1670683038&fvip=4&keepalive=yes&fexp=24001373%2C24007246&c=WEB&n=Q1clxY75jYTz5-Jjs&sparams=expire%2Cei%2Cip%2Cid%2Caitags%2Csource%2Crequiressl%2Cvprv%2Cmime%2Cns%2Cgir%2Cclen%2Cdur%2Clmt&lsparams=mh%2Cmm%2Cmn%2Cms%2Cmv%2Cmvi%2Cpl%2Cinitcwndbps&lsig=AG3C_xAwRQIhALAiXhKHHYyEXqZjplvi1kikA52fe7Atbtf5dMJRzrykAiACfdkp2RJ8mz7ozz05JFbOuF6Oj917lXMLt1nVq8Tbbg%3D%3D&sig=AOq0QJ8wRQIgXsjIxbWugYrsf0Vrwr7ru-i6N5KfbNKXC8JseTpI9vUCIQCBcdQfRbfdJz05dvTuV4saD_OoLF9VxvcpKhCIqtAUNQ==", "width": 320, "ext": "webm", "vcodec": "vp9", "acodec": "none", "vbr": 44.905, "downloader_options": {"http_chunk_size": 10485760}, "container": "webm_dash", "format": "242 - 320x240 (240p)", "protocol": "https", "http_headers": {"User-Agent": "Mozilla/5.0 (Windows NT 10.0; Win64; x64) AppleWebKit/537.36 (KHTML, like Gecko) Chrome/75.0.3761.3 Safari/537.36", "Accept-Charset": "ISO-8859-1,utf-8;q=0.7,*;q=0.7", "Accept": "text/html,application/xhtml+xml,application/xml;q=0.9,*/*;q=0.8", "Accept-Encoding": "gzip, deflate", "Accept-Language": "en-us,en;q=0.5"}}, {"asr": null, "filesize": 1039505, "format_id": "395", "format_note": "240p", "fps": 30, "height": 240, "quality": 1, "tbr": 45.302, "url": "https://rr7---sn-0opoxu-ihvr.googlevideo.com/videoplayback?expire=1670704945&ei=0ZqUY--1JtKtkgb9o6G4Cw&ip=189.173.225.87&id=o-AE0a5LPaEq35nQxd-T_v8UhtPpD_44qWwlufXywortPl&itag=395&aitags=133%2C134%2C135%2C160%2C242%2C243%2C244%2C278%2C394%2C395%2C396%2C397&source=youtube&requiressl=yes&mh=Pw&mm=31%2C29&mn=sn-0opoxu-ihvr%2Csn-q4fl6nlz&ms=au%2Crdu&mv=m&mvi=7&pl=24&initcwndbps=831250&vprv=1&mime=video%2Fmp4&ns=O2TZKNuLSWPWVO3eMbZEI54J&gir=yes&clen=1039505&dur=183.566&lmt=1626223341084195&mt=1670683038&fvip=4&keepalive=yes&fexp=24001373%2C24007246&c=WEB&txp=5436432&n=Q1clxY75jYTz5-Jjs&sparams=expire%2Cei%2Cip%2Cid%2Caitags%2Csource%2Crequiressl%2Cvprv%2Cmime%2Cns%2Cgir%2Cclen%2Cdur%2Clmt&lsparams=mh%2Cmm%2Cmn%2Cms%2Cmv%2Cmvi%2Cpl%2Cinitcwndbps&lsig=AG3C_xAwRAIgP0q9-Sze6mulbH9QZRuiVrEvacj7JdqCrOpkMmxdNXICIHlm2VN7ej5VY6D7iTkOAElfM7NZJ_rcP6U3FrIxBmEw&sig=AOq0QJ8wRQIgeJw2h_1EORFCXk_x5OR3abryucc2wTKa9CPBd63yjicCIQDEcX_1vnirLjw-fYiqjbVE1aF54EW51_WafmJO0BKkSQ==", "width": 320, "ext": "mp4", "vcodec": "av01.0.00M.08", "acodec": "none", "vbr": 45.302, "downloader_options": {"http_chunk_size": 10485760}, "container": "mp4_dash", "format": "395 - 320x240 (240p)", "protocol": "https", "http_headers": {"User-Agent": "Mozilla/5.0 (Windows NT 10.0; Win64; x64) AppleWebKit/537.36 (KHTML, like Gecko) Chrome/75.0.3761.3 Safari/537.36", "Accept-Charset": "ISO-8859-1,utf-8;q=0.7,*;q=0.7", "Accept": "text/html,application/xhtml+xml,application/xml;q=0.9,*/*;q=0.8", "Accept-Encoding": "gzip, deflate", "Accept-Language": "en-us,en;q=0.5"}}, {"asr": null, "filesize": 2066688, "format_id": "133", "format_note": "240p", "fps": 30, "height": 240, "quality": 1, "tbr": 90.084, "url": "https://rr7---sn-0opoxu-ihvr.googlevideo.com/videoplayback?expire=1670704945&ei=0ZqUY--1JtKtkgb9o6G4Cw&ip=189.173.225.87&id=o-AE0a5LPaEq35nQxd-T_v8UhtPpD_44qWwlufXywortPl&itag=133&aitags=133%2C134%2C135%2C160%2C242%2C243%2C244%2C278%2C394%2C395%2C396%2C397&source=youtube&requiressl=yes&mh=Pw&mm=31%2C29&mn=sn-0opoxu-ihvr%2Csn-q4fl6nlz&ms=au%2Crdu&mv=m&mvi=7&pl=24&initcwndbps=831250&vprv=1&mime=video%2Fmp4&ns=O2TZKNuLSWPWVO3eMbZEI54J&gir=yes&clen=2066688&dur=183.534&lmt=1394698809486079&mt=1670683038&fvip=4&keepalive=yes&fexp=24001373%2C24007246&c=WEB&n=Q1clxY75jYTz5-Jjs&sparams=expire%2Cei%2Cip%2Cid%2Caitags%2Csource%2Crequiressl%2Cvprv%2Cmime%2Cns%2Cgir%2Cclen%2Cdur%2Clmt&lsparams=mh%2Cmm%2Cmn%2Cms%2Cmv%2Cmvi%2Cpl%2Cinitcwndbps&lsig=AG3C_xAwRQIgPmrFjNMf6QlK2Qb9GcyrjfuvYTpQ49KgwUfqzBEvdDoCIQCegd6DuyoNAWiThcpLdV2lkyKyylGpCyf1eGk1dgSp7g%3D%3D&sig=AOq0QJ8wRQIgGdDuGZCH9STtif-iHA15Qt_X98B1Fo4Lw9YtB0NRPmgCIQDHtc63uEAXMoCWnGpKBKQZmGSI8pBwFvc-UJjocXZShw==", "width": 320, "ext": "mp4", "vcodec": "avc1.4d400d", "acodec": "none", "vbr": 90.084, "downloader_options": {"http_chunk_size": 10485760}, "container": "mp4_dash", "format": "133 - 320x240 (240p)", "protocol": "https", "http_headers": {"User-Agent": "Mozilla/5.0 (Windows NT 10.0; Win64; x64) AppleWebKit/537.36 (KHTML, like Gecko) Chrome/75.0.3761.3 Safari/537.36", "Accept-Charset": "ISO-8859-1,utf-8;q=0.7,*;q=0.7", "Accept": "text/html,application/xhtml+xml,application/xml;q=0.9,*/*;q=0.8", "Accept-Encoding": "gzip, deflate", "Accept-Language": "en-us,en;q=0.5"}}, {"asr": null, "filesize": 1438886, "format_id": "396", "format_note": "360p", "fps": 30, "height": 360, "quality": 2, "tbr": 62.708, "url": "https://rr7---sn-0opoxu-ihvr.googlevideo.com/videoplayback?expire=1670704945&ei=0ZqUY--1JtKtkgb9o6G4Cw&ip=189.173.225.87&id=o-AE0a5LPaEq35nQxd-T_v8UhtPpD_44qWwlufXywortPl&itag=396&aitags=133%2C134%2C135%2C160%2C242%2C243%2C244%2C278%2C394%2C395%2C396%2C397&source=youtube&requiressl=yes&mh=Pw&mm=31%2C29&mn=sn-0opoxu-ihvr%2Csn-q4fl6nlz&ms=au%2Crdu&mv=m&mvi=7&pl=24&initcwndbps=831250&vprv=1&mime=video%2Fmp4&ns=O2TZKNuLSWPWVO3eMbZEI54J&gir=yes&clen=1438886&dur=183.566&lmt=1626223346389369&mt=1670683038&fvip=4&keepalive=yes&fexp=24001373%2C24007246&c=WEB&txp=5436432&n=Q1clxY75jYTz5-Jjs&sparams=expire%2Cei%2Cip%2Cid%2Caitags%2Csource%2Crequiressl%2Cvprv%2Cmime%2Cns%2Cgir%2Cclen%2Cdur%2Clmt&lsparams=mh%2Cmm%2Cmn%2Cms%2Cmv%2Cmvi%2Cpl%2Cinitcwndbps&lsig=AG3C_xAwRgIhALCopMWiashNcBMU59G6ksDlmNqVYXX6T83yLu0H80jcAiEAw9GhilgC2YLW1h6K8MJO0qsgYcLb_yhh-cdh__IhV8I%3D&sig=AOq0QJ8wRAIgUZv4Pm45rI4HmzeU0POnxtBd3WPrX0RshKNUxsLuYcMCIHyk0rxdX9gjBvO0IWkxl9I_muMRV10S0mnZI7dsARqP", "width": 480, "ext": "mp4", "vcodec": "av01.0.01M.08", "acodec": "none", "vbr": 62.708, "downloader_options": {"http_chunk_size": 10485760}, "container": "mp4_dash", "format": "396 - 480x360 (360p)", "protocol": "https", "http_headers": {"User-Agent": "Mozilla/5.0 (Windows NT 10.0; Win64; x64) AppleWebKit/537.36 (KHTML, like Gecko) Chrome/75.0.3761.3 Safari/537.36", "Accept-Charset": "ISO-8859-1,utf-8;q=0.7,*;q=0.7", "Accept": "text/html,application/xhtml+xml,application/xml;q=0.9,*/*;q=0.8", "Accept-Encoding": "gzip, deflate", "Accept-Language": "en-us,en;q=0.5"}}, {"asr": null, "filesize": 1688484, "format_id": "243", "format_note": "360p", "fps": 30, "height": 360, "quality": 2, "tbr": 73.599, "url": "https://rr7---sn-0opoxu-ihvr.googlevideo.com/videoplayback?expire=1670704945&ei=0ZqUY--1JtKtkgb9o6G4Cw&ip=189.173.225.87&id=o-AE0a5LPaEq35nQxd-T_v8UhtPpD_44qWwlufXywortPl&itag=243&aitags=133%2C134%2C135%2C160%2C242%2C243%2C244%2C278%2C394%2C395%2C396%2C397&source=youtube&requiressl=yes&mh=Pw&mm=31%2C29&mn=sn-0opoxu-ihvr%2Csn-q4fl6nlz&ms=au%2Crdu&mv=m&mvi=7&pl=24&initcwndbps=831250&vprv=1&mime=video%2Fwebm&ns=O2TZKNuLSWPWVO3eMbZEI54J&gir=yes&clen=1688484&dur=183.533&lmt=1497149187945515&mt=1670683038&fvip=4&keepalive=yes&fexp=24001373%2C24007246&c=WEB&n=Q1clxY75jYTz5-Jjs&sparams=expire%2Cei%2Cip%2Cid%2Caitags%2Csource%2Crequiressl%2Cvprv%2Cmime%2Cns%2Cgir%2Cclen%2Cdur%2Clmt&lsparams=mh%2Cmm%2Cmn%2Cms%2Cmv%2Cmvi%2Cpl%2Cinitcwndbps&lsig=AG3C_xAwRAIgDvW3uXw2X0dPFzCyB2q8zc7E-9TJuwRZLtS84gsu25ACIHB0eO6VhZTEIJ6nFhjMNX4IZqGGSq4bVyjxHq3VP0CE&sig=AOq0QJ8wRQIgG8sVGvzUKOWi3NlLjj8KDKou_VpX7sQ426kl6mr9zUcCIQCnfI3-gvGLfZ4f-vQ34UfwMPkK1dio-Ml2nLu9r4OyZg==", "width": 480, "ext": "webm", "vcodec": "vp9", "acodec": "none", "vbr": 73.599, "downloader_options": {"http_chunk_size": 10485760}, "container": "webm_dash", "format": "243 - 480x360 (360p)", "protocol": "https", "http_headers": {"User-Agent": "Mozilla/5.0 (Windows NT 10.0; Win64; x64) AppleWebKit/537.36 (KHTML, like Gecko) Chrome/75.0.3761.3 Safari/537.36", "Accept-Charset": "ISO-8859-1,utf-8;q=0.7,*;q=0.7", "Accept": "text/html,application/xhtml+xml,application/xml;q=0.9,*/*;q=0.8", "Accept-Encoding": "gzip, deflate", "Accept-Language": "en-us,en;q=0.5"}}, {"asr": null, "filesize": 3519874, "format_id": "134", "format_note": "360p", "fps": 30, "height": 360, "quality": 2, "tbr": 153.426, "url": "https://rr7---sn-0opoxu-ihvr.googlevideo.com/videoplayback?expire=1670704945&ei=0ZqUY--1JtKtkgb9o6G4Cw&ip=189.173.225.87&id=o-AE0a5LPaEq35nQxd-T_v8UhtPpD_44qWwlufXywortPl&itag=134&aitags=133%2C134%2C135%2C160%2C242%2C243%2C244%2C278%2C394%2C395%2C396%2C397&source=youtube&requiressl=yes&mh=Pw&mm=31%2C29&mn=sn-0opoxu-ihvr%2Csn-q4fl6nlz&ms=au%2Crdu&mv=m&mvi=7&pl=24&initcwndbps=831250&vprv=1&mime=video%2Fmp4&ns=O2TZKNuLSWPWVO3eMbZEI54J&gir=yes&clen=3519874&dur=183.534&lmt=1394698812937333&mt=1670683038&fvip=4&keepalive=yes&fexp=24001373%2C24007246&c=WEB&n=Q1clxY75jYTz5-Jjs&sparams=expire%2Cei%2Cip%2Cid%2Caitags%2Csource%2Crequiressl%2Cvprv%2Cmime%2Cns%2Cgir%2Cclen%2Cdur%2Clmt&lsparams=mh%2Cmm%2Cmn%2Cms%2Cmv%2Cmvi%2Cpl%2Cinitcwndbps&lsig=AG3C_xAwRQIhAO7-mkeZH_hcpECTza7htxEWEffDlxhyt7rtgSwpQkRwAiAVIEXfXavRZWNEz5ne-fzLZiiqB0d7UBa0ogoxSdZk5w%3D%3D&sig=AOq0QJ8wRgIhAI9yEdHAmZwb74-vnVT5B05clPM7fPj9oqcnzMDdaV11AiEA6agJaFsEzTCY6T0wi-acGfUeTmiaFTjnZsrgUgICcno=", "width": 480, "ext": "mp4", "vcodec": "avc1.4d401e", "acodec": "none", "vbr": 153.426, "downloader_options": {"http_chunk_size": 10485760}, "container": "mp4_dash", "format": "134 - 480x360 (360p)", "protocol": "https", "http_headers": {"User-Agent": "Mozilla/5.0 (Windows NT 10.0; Win64; x64) AppleWebKit/537.36 (KHTML, like Gecko) Chrome/75.0.3761.3 Safari/537.36", "Accept-Charset": "ISO-8859-1,utf-8;q=0.7,*;q=0.7", "Accept": "text/html,application/xhtml+xml,application/xml;q=0.9,*/*;q=0.8", "Accept-Encoding": "gzip, deflate", "Accept-Language": "en-us,en;q=0.5"}}, {"asr": null, "filesize": 1965309, "format_id": "397", "format_note": "480p", "fps": 30, "height": 480, "quality": 3, "tbr": 85.65, "url": "https://rr7---sn-0opoxu-ihvr.googlevideo.com/videoplayback?expire=1670704945&ei=0ZqUY--1JtKtkgb9o6G4Cw&ip=189.173.225.87&id=o-AE0a5LPaEq35nQxd-T_v8UhtPpD_44qWwlufXywortPl&itag=397&aitags=133%2C134%2C135%2C160%2C242%2C243%2C244%2C278%2C394%2C395%2C396%2C397&source=youtube&requiressl=yes&mh=Pw&mm=31%2C29&mn=sn-0opoxu-ihvr%2Csn-q4fl6nlz&ms=au%2Crdu&mv=m&mvi=7&pl=24&initcwndbps=831250&vprv=1&mime=video%2Fmp4&ns=O2TZKNuLSWPWVO3eMbZEI54J&gir=yes&clen=1965309&dur=183.566&lmt=1626223344883943&mt=1670683038&fvip=4&keepalive=yes&fexp=24001373%2C24007246&c=WEB&txp=5436432&n=Q1clxY75jYTz5-Jjs&sparams=expire%2Cei%2Cip%2Cid%2Caitags%2Csource%2Crequiressl%2Cvprv%2Cmime%2Cns%2Cgir%2Cclen%2Cdur%2Clmt&lsparams=mh%2Cmm%2Cmn%2Cms%2Cmv%2Cmvi%2Cpl%2Cinitcwndbps&lsig=AG3C_xAwRQIgTkB7mXBh4cB7GKF0w2Usi0CR-2wtAD5-_NztvhDDxDgCIQDtqJUuqXutaSFVJL70SiiMXGQhmlxejmN9Mlo8QJzV5g%3D%3D&sig=AOq0QJ8wRQIhAJ7E-h_mMD4nagNh-hNMbbf3nfBFHfEsXK7rvk8WtXQbAiAnjuulxPDW2pSuUf5k7ZVdGm0wJTr4lLl28ozmkDt-gw==", "width": 640, "ext": "mp4", "vcodec": "av01.0.04M.08", "acodec": "none", "vbr": 85.65, "downloader_options": {"http_chunk_size": 10485760}, "container": "mp4_dash", "format": "397 - 640x480 (480p)", "protocol": "https", "http_headers": {"User-Agent": "Mozilla/5.0 (Windows NT 10.0; Win64; x64) AppleWebKit/537.36 (KHTML, like Gecko) Chrome/75.0.3761.3 Safari/537.36", "Accept-Charset": "ISO-8859-1,utf-8;q=0.7,*;q=0.7", "Accept": "text/html,application/xhtml+xml,application/xml;q=0.9,*/*;q=0.8", "Accept-Encoding": "gzip, deflate", "Accept-Language": "en-us,en;q=0.5"}}, {"asr": null, "filesize": 2433402, "format_id": "244", "format_note": "480p", "fps": 30, "height": 480, "quality": 3, "tbr": 106.069, "url": "https://rr7---sn-0opoxu-ihvr.googlevideo.com/videoplayback?expire=1670704945&ei=0ZqUY--1JtKtkgb9o6G4Cw&ip=189.173.225.87&id=o-AE0a5LPaEq35nQxd-T_v8UhtPpD_44qWwlufXywortPl&itag=244&aitags=133%2C134%2C135%2C160%2C242%2C243%2C244%2C278%2C394%2C395%2C396%2C397&source=youtube&requiressl=yes&mh=Pw&mm=31%2C29&mn=sn-0opoxu-ihvr%2Csn-q4fl6nlz&ms=au%2Crdu&mv=m&mvi=7&pl=24&initcwndbps=831250&vprv=1&mime=video%2Fwebm&ns=O2TZKNuLSWPWVO3eMbZEI54J&gir=yes&clen=2433402&dur=183.533&lmt=1497149186775683&mt=1670683038&fvip=4&keepalive=yes&fexp=24001373%2C24007246&c=WEB&n=Q1clxY75jYTz5-Jjs&sparams=expire%2Cei%2Cip%2Cid%2Caitags%2Csource%2Crequiressl%2Cvprv%2Cmime%2Cns%2Cgir%2Cclen%2Cdur%2Clmt&lsparams=mh%2Cmm%2Cmn%2Cms%2Cmv%2Cmvi%2Cpl%2Cinitcwndbps&lsig=AG3C_xAwRQIhAK1YQkVxo89yzsFkpFeE2JZvhGD7Eim9Sp4PMePJBwcEAiB98MRlLLi9fQxy4S-X2JeWaHSPn97pYRHhAIZmeARa4Q%3D%3D&sig=AOq0QJ8wRgIhAKfi56jjcN-LHpPWQYBgH7jMEiD4Bo9UoE8MQwFJ4UWtAiEAl1NjqPnXZjcj2fucNfmPPHpEFxzJDqGzekOV2yCV49I=", "width": 640, "ext": "webm", "vcodec": "vp9", "acodec": "none", "vbr": 106.069, "downloader_options": {"http_chunk_size": 10485760}, "container": "webm_dash", "format": "244 - 640x480 (480p)", "protocol": "https", "http_headers": {"User-Agent": "Mozilla/5.0 (Windows NT 10.0; Win64; x64) AppleWebKit/537.36 (KHTML, like Gecko) Chrome/75.0.3761.3 Safari/537.36", "Accept-Charset": "ISO-8859-1,utf-8;q=0.7,*;q=0.7", "Accept": "text/html,application/xhtml+xml,application/xml;q=0.9,*/*;q=0.8", "Accept-Encoding": "gzip, deflate", "Accept-Language": "en-us,en;q=0.5"}}, {"asr": null, "filesize": 5381007, "format_id": "135", "format_note": "480p", "fps": 30, "height": 480, "quality": 3, "tbr": 234.55, "url": "https://rr7---sn-0opoxu-ihvr.googlevideo.com/videoplayback?expire=1670704945&ei=0ZqUY--1JtKtkgb9o6G4Cw&ip=189.173.225.87&id=o-AE0a5LPaEq35nQxd-T_v8UhtPpD_44qWwlufXywortPl&itag=135&aitags=133%2C134%2C135%2C160%2C242%2C243%2C244%2C278%2C394%2C395%2C396%2C397&source=youtube&requiressl=yes&mh=Pw&mm=31%2C29&mn=sn-0opoxu-ihvr%2Csn-q4fl6nlz&ms=au%2Crdu&mv=m&mvi=7&pl=24&initcwndbps=831250&vprv=1&mime=video%2Fmp4&ns=O2TZKNuLSWPWVO3eMbZEI54J&gir=yes&clen=5381007&dur=183.534&lmt=1394698816169921&mt=1670683038&fvip=4&keepalive=yes&fexp=24001373%2C24007246&c=WEB&n=Q1clxY75jYTz5-Jjs&sparams=expire%2Cei%2Cip%2Cid%2Caitags%2Csource%2Crequiressl%2Cvprv%2Cmime%2Cns%2Cgir%2Cclen%2Cdur%2Clmt&lsparams=mh%2Cmm%2Cmn%2Cms%2Cmv%2Cmvi%2Cpl%2Cinitcwndbps&lsig=AG3C_xAwRAIgNCUbsBy_SXYZ_iQ_43f3T6ojfbvAzL92NfXZ3fZte4oCIDOiOOGUhg54LGnq0nMT7_7llX51PX6cvKn-rHRmm1Yf&sig=AOq0QJ8wRgIhAKt_rAx5NzJHL-MasI8D6Dv6IiwQRA4uYnaR8Ze3nOg0AiEA9B5BWt-K2D1mEAh8AUx2GrOsqkyvvEETxI-NfpJaZhU=", "width": 640, "ext": "mp4", "vcodec": "avc1.4d401e", "acodec": "none", "vbr": 234.55, "downloader_options": {"http_chunk_size": 10485760}, "container": "mp4_dash", "format": "135 - 640x480 (480p)", "protocol": "https", "http_headers": {"User-Agent": "Mozilla/5.0 (Windows NT 10.0; Win64; x64) AppleWebKit/537.36 (KHTML, like Gecko) Chrome/75.0.3761.3 Safari/537.36", "Accept-Charset": "ISO-8859-1,utf-8;q=0.7,*;q=0.7", "Accept": "text/html,application/xhtml+xml,application/xml;q=0.9,*/*;q=0.8", "Accept-Encoding": "gzip, deflate", "Accept-Language": "en-us,en;q=0.5"}}, {"asr": 22050, "filesize": null, "format_id": "18", "format_note": "360p", "fps": 30, "height": 360, "quality": 2, "tbr": 199.047, "url": "https://rr7---sn-0opoxu-ihvr.googlevideo.com/videoplayback?expire=1670704945&ei=0ZqUY--1JtKtkgb9o6G4Cw&ip=189.173.225.87&id=o-AE0a5LPaEq35nQxd-T_v8UhtPpD_44qWwlufXywortPl&itag=18&source=youtube&requiressl=yes&mh=Pw&mm=31%2C29&mn=sn-0opoxu-ihvr%2Csn-q4fl6nlz&ms=au%2Crdu&mv=m&mvi=7&pl=24&initcwndbps=831250&vprv=1&xtags=heaudio%3Dtrue&mime=video%2Fmp4&ns=weuabbvhSigXGRuc8Lgc4I4J&cnr=14&ratebypass=yes&dur=183.762&lmt=1666478947019393&mt=1670683038&fvip=4&fexp=24001373%2C24007246&c=WEB&txp=1438434&n=qeIO_xuek9KV1-v3a&sparams=expire%2Cei%2Cip%2Cid%2Citag%2Csource%2Crequiressl%2Cvprv%2Cxtags%2Cmime%2Cns%2Ccnr%2Cratebypass%2Cdur%2Clmt&lsparams=mh%2Cmm%2Cmn%2Cms%2Cmv%2Cmvi%2Cpl%2Cinitcwndbps&lsig=AG3C_xAwRgIhAMfXBQ6bh-9lDQYuZ0dkPimDK-Rizi2X_IFT-3Lm5jguAiEAk6z4BkrEUkmnYvI_uV56KQm3LkdNu7fSnBPNZVohHH8%3D&sig=AOq0QJ8wRgIhAKrED0XuZdOswyrvncIXTl0IKV5iiMAdoe2bdCc0lQb8AiEAztmwQWxFSv_tpUFvSPN-O0IueCtVcibBIIQoJR0ZdkA=", "width": 480, "ext": "mp4", "vcodec": "avc1.42001E", "acodec": "mp4a.40.2", "format": "18 - 480x360 (360p)", "protocol": "https", "http_headers": {"User-Agent": "Mozilla/5.0 (Windows NT 10.0; Win64; x64) AppleWebKit/537.36 (KHTML, like Gecko) Chrome/75.0.3761.3 Safari/537.36", "Accept-Charset": "ISO-8859-1,utf-8;q=0.7,*;q=0.7", "Accept": "text/html,application/xhtml+xml,application/xml;q=0.9,*/*;q=0.8", "Accept-Encoding": "gzip, deflate", "Accept-Language": "en-us,en;q=0.5"}}], "thumbnails": [{"height": 94, "url": "https://i.ytimg.com/vi/2u_pEd4_2cI/hqdefault.jpg?sqp=-oaymwEbCKgBEF5IVfKriqkDDggBFQAAiEIYAXABwAEG&rs=AOn4CLBfCDZMSv35NFIsW8zLf7vnlfHVZg", "width": 168, "resolution": "168x94", "id": "0"}, {"height": 110, "url": "https://i.ytimg.com/vi/2u_pEd4_2cI/hqdefault.jpg?sqp=-oaymwEbCMQBEG5IVfKriqkDDggBFQAAiEIYAXABwAEG&rs=AOn4CLAFswGBuUIwT0T4-mAb7E_XEbeUTg", "width": 196, "resolution": "196x110", "id": "1"}, {"height": 138, "url": "https://i.ytimg.com/vi/2u_pEd4_2cI/hqdefault.jpg?sqp=-oaymwEcCPYBEIoBSFXyq4qpAw4IARUAAIhCGAFwAcABBg==&rs=AOn4CLBhmOMUbeC_WRF4QByoACzwQxtAiQ", "width": 246, "resolution": "246x138", "id": "2"}, {"height": 188, "url": "https://i.ytimg.com/vi/2u_pEd4_2cI/hqdefault.jpg?sqp=-oaymwEcCNACELwBSFXyq4qpAw4IARUAAIhCGAFwAcABBg==&rs=AOn4CLAB_7_VYtKIoxDxMr5sQJMdG0yEVQ", "width": 336, "resolution": "336x188", "id": "3"}], "description": "ey ey ey!\n\nay viene la buchona vestida y a la moda,\nsus unas decoradas su boca bien pintada,\nay viene ya la plebe montada en su cheyyenne\ncon musica de banda corridos suene y suene..\n\nbotellas de buchanas lleva por el malecon\nque buena esta la fiesta que empieze el pachangon...\n\ney ey ey!\n\n((MUSICA))\n\nyo tengo una vecina que es muy coquetona\nle gusta hablar de party es una buchona\nle gusta tomar whisky y tambien tequila\nle gusta (tomar conyac/parandear) junto con sus amigas\n\nay viene la buchona vestida y a la moda\nsus unas decoradas su boca bien pintada,\nay viene ya la plebe montada en su cheyyenne\ncon musica de banda corridos suene y suene..\n\nbotellas de buchanas lleva por el malecon\nque buena esta la fiesta que empieze el pachangon...\n\nyo tengo un vecina...\nay viene la buchona...\n**repertir**", "upload_date": "20111126", "uploader": "HollisterSwagg1000", "uploader_id": "HollisterSwagg1000", "uploader_url": "http://www.youtube.com/user/HollisterSwagg1000", "channel_id": "UCkDTXX8Ajd81am6tJ2S0EDw", "channel_url": "https://www.youtube.com/channel/UCkDTXX8Ajd81am6tJ2S0EDw", "duration": 184, "view_count": 2035596, "average_rating": null, "age_limit": 0, "webpage_url": "https://www.youtube.com/watch?v=2u_pEd4_2cI", "categories": ["Music"], "tags": ["CHUY", "LIZARRAGA", "LA", "BUCHONA"], "is_live": null, "channel": "HollisterSwagg1000", "extractor": "youtube", "webpage_url_basename": "watch", "extractor_key": "Youtube", "playlist": null, "playlist_index": null, "thumbnail": "https://i.ytimg.com/vi/2u_pEd4_2cI/hqdefault.jpg?sqp=-oaymwEcCNACELwBSFXyq4qpAw4IARUAAIhCGAFwAcABBg==&rs=AOn4CLAB_7_VYtKIoxDxMr5sQJMdG0yEVQ", "display_id": "2u_pEd4_2cI", "asr": 22050, "filesize": null, "format_id": "18", "format_note": "360p", "fps": 30, "height": 360, "quality": 2, "tbr": 199.047, "url": "https://rr7---sn-0opoxu-ihvr.googlevideo.com/videoplayback?expire=1670704945&ei=0ZqUY--1JtKtkgb9o6G4Cw&ip=189.173.225.87&id=o-AE0a5LPaEq35nQxd-T_v8UhtPpD_44qWwlufXywortPl&itag=18&source=youtube&requiressl=yes&mh=Pw&mm=31%2C29&mn=sn-0opoxu-ihvr%2Csn-q4fl6nlz&ms=au%2Crdu&mv=m&mvi=7&pl=24&initcwndbps=831250&vprv=1&xtags=heaudio%3Dtrue&mime=video%2Fmp4&ns=weuabbvhSigXGRuc8Lgc4I4J&cnr=14&ratebypass=yes&dur=183.762&lmt=1666478947019393&mt=1670683038&fvip=4&fexp=24001373%2C24007246&c=WEB&txp=1438434&n=qeIO_xuek9KV1-v3a&sparams=expire%2Cei%2Cip%2Cid%2Citag%2Csource%2Crequiressl%2Cvprv%2Cxtags%2Cmime%2Cns%2Ccnr%2Cratebypass%2Cdur%2Clmt&lsparams=mh%2Cmm%2Cmn%2Cms%2Cmv%2Cmvi%2Cpl%2Cinitcwndbps&lsig=AG3C_xAwRgIhAMfXBQ6bh-9lDQYuZ0dkPimDK-Rizi2X_IFT-3Lm5jguAiEAk6z4BkrEUkmnYvI_uV56KQm3LkdNu7fSnBPNZVohHH8%3D&sig=AOq0QJ8wRgIhAKrED0XuZdOswyrvncIXTl0IKV5iiMAdoe2bdCc0lQb8AiEAztmwQWxFSv_tpUFvSPN-O0IueCtVcibBIIQoJR0ZdkA=", "width": 480, "ext": "mp4", "vcodec": "avc1.42001E", "acodec": "mp4a.40.2", "format": "18 - 480x360 (360p)", "protocol": "https", "http_headers": {"User-Agent": "Mozilla/5.0 (Windows NT 10.0; Win64; x64) AppleWebKit/537.36 (KHTML, like Gecko) Chrome/75.0.3761.3 Safari/537.36", "Accept-Charset": "ISO-8859-1,utf-8;q=0.7,*;q=0.7", "Accept": "text/html,application/xhtml+xml,application/xml;q=0.9,*/*;q=0.8", "Accept-Encoding": "gzip, deflate", "Accept-Language": "en-us,en;q=0.5"}, "fulltitle": "CHUY LIZARRAGA - LA BUCHONA con letra", "_filename": "CHUY LIZARRAGA - LA BUCHONA con letra-2u_pEd4_2cI.mp4"}